smpq.py
smpq-0.1.dist-info/DESCRIPTION.rst
smpq-0.1.dist-info/METADATA
smpq-0.1.dist-info/RECORD
smpq-0.1.dist-info/WHEEL
smpq-0.1.dist-info/metadata.json
smpq-0.1.dist-info/top_level.txt
