Metadata-Version: 2.0
Name: smpq
Version: 0.1
Summary: Simple Multiprocessing Queue
Home-page: http://github.com/strangemother/smpq
Author: Jay Jagpal
Author-email: jay@strangemother.com
License: MIT
Platform: UNKNOWN
